.travis.yml
NOTICE.txt
README.rst
bootstrap.py
buildout.cfg
eke.publications.sublime-project
setup.cfg
setup.py
travis.cfg
docs/HISTORY.txt
docs/INSTALL.txt
docs/LICENSE.txt
eke/__init__.py
eke.publications.egg-info/PKG-INFO
eke.publications.egg-info/SOURCES.txt
eke.publications.egg-info/dependency_links.txt
eke.publications.egg-info/entry_points.txt
eke.publications.egg-info/namespace_packages.txt
eke.publications.egg-info/not-zip-safe
eke.publications.egg-info/requires.txt
eke.publications.egg-info/top_level.txt
eke/publications/README.rst
eke/publications/__init__.py
eke/publications/config.py
eke/publications/configure.zcml
eke/publications/interfaces.py
eke/publications/overrides.zcml
eke/publications/testing.py
eke/publications/upgrades.py
eke/publications/upgrades.zcml
eke/publications/utils.py
eke/publications/browser/__init__.py
eke/publications/browser/configure.zcml
eke/publications/browser/eke-publications.css
eke/publications/browser/rdf.py
eke/publications/browser/views.py
eke/publications/browser/images/publication-folder.gif
eke/publications/browser/images/publication.gif
eke/publications/browser/templates/publication.pt
eke/publications/browser/templates/publication_timeline_report.pt
eke/publications/browser/templates/publicationfolder.pt
eke/publications/content/__init__.py
eke/publications/content/configure.zcml
eke/publications/content/publication.py
eke/publications/content/publicationfolder.py
eke/publications/profiles/default/catalog.xml
eke/publications/profiles/default/factorytool.xml
eke/publications/profiles/default/metadata.xml
eke/publications/profiles/default/portal_atct.xml
eke/publications/profiles/default/rolemap.xml
eke/publications/profiles/default/types.xml
eke/publications/profiles/default/types/Publication.xml
eke/publications/profiles/default/types/Publication_Folder.xml
eke/publications/templates/faceted_publications_view.pt
eke/publications/templates/faceted_publications_view.pt.metadata
eke/publications/tests/__init__.py
eke/publications/tests/base.py
eke/publications/tests/testDoctest.py
eke/publications/tests/testSetup.py